pdf_table_builder/__init__.py
pdf_table_builder/builder.py
pdf_table_builder/consts.py
pdf_table_builder/helpers.py
pdf_table_builder/__pycache__/__init__.cpython-38.pyc
pdf_table_builder/__pycache__/builder.cpython-38.pyc
pdf_table_builder/__pycache__/helpers.cpython-38.pyc
pdf_table_builder/fonts/NotoSans-Bold.ttf
pdf_table_builder/fonts/NotoSans-Regular.ttf
pdf_table_builder/utils/helpers.py
reportlab_pdf_table_builder-1.1.8.dist-info/LICENSE
reportlab_pdf_table_builder-1.1.8.dist-info/METADATA
reportlab_pdf_table_builder-1.1.8.dist-info/WHEEL
reportlab_pdf_table_builder-1.1.8.dist-info/top_level.txt
reportlab_pdf_table_builder-1.1.8.dist-info/RECORD
