Metadata-Version: 2.1
Name: reportlab-pdf-table-builder
Version: 1.1.8
Summary: A simple pdf table builder using the ReportLab Toolkit
Home-page: https://github.com/timossavva/reportlab-pdf-table-builder
Author: Timotheos Savva
Author-email: timotheos.savva12@gmail.com
Classifier: Programming Language :: Python :: 3
Classifier: License :: OSI Approved :: MIT License
Classifier: Operating System :: OS Independent
Requires-Python: >=3.6
License-File: LICENSE
Requires-Dist: reportlab (>=3.6.5)
Requires-Dist: Pillow (>=9.0.1)
